cdBoundary/__init__.py
cdBoundary/_modidx.py
cdBoundary/boundary.py
cdBoundary/fileio.py
cdBoundary-0.8.dist-info/LICENSE
cdBoundary-0.8.dist-info/METADATA
cdBoundary-0.8.dist-info/WHEEL
cdBoundary-0.8.dist-info/entry_points.txt
cdBoundary-0.8.dist-info/top_level.txt
cdBoundary-0.8.dist-info/RECORD
