Metadata-Version: 2.1
Name: cdBoundary
Version: 0.8
Summary: Concave hull by distance
Home-page: https://github.com/civildot/cdBoundary
Author: André Kruger
Author-email: andrelester32@gmail.com
License: MIT License
Keywords: nbdev jupyter notebook python
Classifier: Development Status :: 5 - Production/Stable
Classifier: Intended Audience :: Developers
Classifier: Natural Language :: English
Classifier: Programming Language :: Python :: 3.7
Classifier: Programming Language :: Python :: 3.8
Classifier: Programming Language :: Python :: 3.9
Classifier: Programming Language :: Python :: 3.10
Classifier: License :: OSI Approved :: MIT License
Requires-Python: >=3.7
License-File: LICENSE
Requires-Dist: shapely
Requires-Dist: matplotlib
Requires-Dist: fiona (>=1.9.4)
Requires-Dist: numpy
Provides-Extra: dev
Requires-Dist: tabulate ; extra == 'dev'
